pytorch_image/__init__.py
pytorch_image/image.py
pytorch_image-1.0.2.dist-info/METADATA
pytorch_image-1.0.2.dist-info/WHEEL
pytorch_image-1.0.2.dist-info/RECORD
