Metadata-Version: 2.1
Name: pytorch-image
Version: 1.0.2
Summary: Minimalistic library designed to be an interface for the model input with a lightweight `Image` class.
License: MIT
Author: Richard Löwenström
Author-email: samedii@gmail.com
Requires-Python: >=3.8,<3.11
Classifier: License :: OSI Approved :: MIT License
Classifier: Programming Language :: Python :: 3
Classifier: Programming Language :: Python :: 3.8
Classifier: Programming Language :: Python :: 3.9
Classifier: Programming Language :: Python :: 3.10
Provides-Extra: train
Requires-Dist: albumentations ; extra == "train"
Requires-Dist: numpy
Requires-Dist: pillow
Requires-Dist: pydantic (>=2.0.0,<3.0.0)
Requires-Dist: torch
